videohash/__init__.py
videohash/__version__.py
videohash/collagemaker.py
videohash/downloader.py
videohash/exceptions.py
videohash/framesextractor.py
videohash/tilemaker.py
videohash/utils.py
videohash/videoduration.py
videohash/videohash.py
videohash-3.0.1.dist-info/LICENSE
videohash-3.0.1.dist-info/METADATA
videohash-3.0.1.dist-info/WHEEL
videohash-3.0.1.dist-info/top_level.txt
videohash-3.0.1.dist-info/RECORD
