Metadata-Version: 2.1
Name: videohash
Version: 3.0.1
Summary: Python package for Near Duplicate Video Detection (Perceptual Video Hashing) - Get a 64-bit comparable hash-value for any video.
Home-page: https://akamhy.github.io/videohash/
Author: Akash Mahanty
Author-email: akamhy@yahoo.com
License: MIT
Download-URL: https://github.com/akamhy/videohash/archive/3.0.1.tar.gz
Project-URL: Source, https://github.com/akamhy/videohash
Project-URL: Documentation, https://github.com/akamhy/videohash/wiki
Project-URL: Tracker, https://github.com/akamhy/videohash/issues
Keywords: videohash,near duplicate video detection,NDVD,perceptual video hashing,video hashing,near duplicate video,compare videos,video,video diff
Platform: UNKNOWN
Classifier: Development Status :: 5 - Production/Stable
Classifier: Intended Audience :: Developers
Classifier: Intended Audience :: End Users/Desktop
Classifier: Intended Audience :: Information Technology
Classifier: Operating System :: MacOS
Classifier: Operating System :: Microsoft :: Windows
Classifier: Operating System :: POSIX
Classifier: Operating System :: POSIX :: Linux
Classifier: Operating System :: POSIX :: BSD
Classifier: Topic :: Multimedia :: Video
Classifier: Natural Language :: English
Classifier: Topic :: Software Development :: Build Tools
Classifier: Topic :: Scientific/Engineering :: Image Recognition
Classifier: Typing :: Typed
Classifier: License :: OSI Approved :: MIT License
Classifier: Programming Language :: Python
Classifier: Programming Language :: Python :: 3
Classifier: Programming Language :: Python :: 3.6
Classifier: Programming Language :: Python :: 3.7
Classifier: Programming Language :: Python :: 3.8
Classifier: Programming Language :: Python :: 3.9
Classifier: Programming Language :: Python :: 3.10
Classifier: Programming Language :: Python :: Implementation :: CPython
Requires-Python: >=3.6
License-File: LICENSE
